{
  "date": "2026-06-22",
  "generatedAt": "2026-06-22T09:45:00+08:00",
  "executionNote": "Day 58·09:45二次刷新——早间09:00首报后追加SS Micron DDR5/ CDW双SKU/ SHI/ Tech-America/ PM1763 Gen6/ 247WallSt 等验证。WF6危机6/19解除确认。DRAMeXchange四天空窗(端午+周末),今晚~18:00 session检验$47。全18列持平(无新spot)。MLC 8天+Micron 6/24仅2天+MU$1,134 ATH。",
  "coverage": {
    "DDR5-6400": {"filled": 3, "total": 3},
    "DDR5-5600": {"filled": 3, "total": 3},
    "PCIe4 TLC": {"filled": 4, "total": 4},
    "PCIe5 TLC": {"filled": 4, "total": 4},
    "PCIe4 QLC": {"filled": 4, "total": 4}
  },
  "newSourcesTried": [
    "ServerSupply Micron DDR5-6400 32GB/64GB (new pricing cross-verify)",
    "CDW dual SKU verification (#8215729 8-10+Days vs #8455187 Backordered)",
    "SHI 9550 Pro 30.72TB Backordered Day 27",
    "Tech-America QLC 61.44TB $24,676",
    "247WallSt Micron sell-the-news risk (June 21)",
    "Wiredzone 9550 Pro In Stock (Email For Price)"
  ],
  "newSourcesWithUsefulData": [
    "ServerSupply Micron DDR5-6400 (32GB $1,345/64GB $2,530)",
    "CDW dual SKU (consumer improving vs 10-pack backordered)",
    "SHI (Backordered Day 27 stability)",
    "Tech-America QLC ($24,676)"
  ],
  "keyChangesVsYesterday": [
    "WF6供给危机正式解除(6/19日本厂商暂停停产→6/22多方确认)",
    "'双重供给收缩'(MLC+WF6)叙事瓦解→仅剩MLC单一收缩(8天)",
    "PCIe5 TLC从buy_now降级为split_buy(WF6解除+PM1763 Gen6压价)",
    "CDW 9550 Pro consumer 8-10+Days vs 10-pack Backordered双SKU分化确认",
    "Mouser QLC 61.44TB U.2库存从昨日4台→今日搜索模糊(1-5台),需定向验证",
    "247WallSt 6/21预警Micron 6/24 sell-the-news风险",
    "ServerSupply Micron DDR5-6400 32GB新货$1,345(NEMIX$1,488零售溢价+10.6%)",
    "Samsung PM1763 PCIe Gen6对PCIe5 TLC中期技术迭代压力量化"
  ],
  "trendJudgement": {
    "DDR5-6400": "up",
    "DDR5-5600": "up",
    "PCIe4 TLC": "flat",
    "PCIe5 TLC": "volatility_expand",
    "PCIe4 QLC": "volatility_expand"
  },
  "procurementView": {
    "DDR5-6400": {
      "recommendation": "buy_now",
      "reason": "DDR5 spot $46.000十七连ATH。自5/20 $41.100累计+11.92%。DRAM Q1 +90-95% QoQ,Q2 +58-63%。SK Hynix/Samsung 2026全链售罄。NEMIX$1,488维持58天,零售补涨压力达历史峰值。今晚session若突破$47将触发零售调价窗口急剧收窄。建议在零售末班车关闭前执行采购。"
    },
    "DDR5-5600": {
      "recommendation": "buy_now",
      "reason": "DDR5 spot $46.000同步ATH。DDR4 16Gb $69.125逼近$70→高密度DDR4/DDR5价差收窄→更多买方切换至DDR5。DDR4→DDR3→DDR5全链溢出效应第十一天加速。DRAM产能向HBM4转移(Line 12转换)挤压标准DRAM供给。建议在今晚session可能出现的新ATH前执行。"
    },
    "PCIe4 TLC": {
      "recommendation": "buy_now",
      "reason": "MLC NAND仅剩8天——最终停产。Samsung Line 12→HBM4 DRAM转换物理确认。NAND Q2 +70-75% QoQ,2026全链售罄。Gartner NAND +234%年度。尽管WF6危机解除降低部分压力,MLC单一收缩仍构成充分的立即采购理由。PM1733停产+PM9A3清仓降价≠新货充足。品牌裂口2.5-2.7x(Day 51)暗示新旧货源市场严重割裂。MLC溢出效应8天内不可替代。"
    },
    "PCIe5 TLC": {
      "recommendation": "split_buy",
      "reason": "WF6危机解除→降级从buy_now至split_buy。Newegg OOS Day 15仍构成零售紧张信号,但CDW改善至8-10+Days+SS$17,700 Day 49稳定+Wiredzone In Stock+Thinkmate新渠道→多源可得性维持。Samsung PM1763 Gen6 SSD(28,400MB/s)已推出→中期技术迭代压力将抑制PCIe5 TLC过度囤货的回报。MLC 8天溢出效应仍构成部分采购理由但恐慌性囤货已不必要。分批采购：部分立即执行锁定供给,部分观望6/24 Micron财报后决策。"
    },
    "PCIe4 QLC": {
      "recommendation": "split_buy",
      "reason": "WF6危机解除是最重大结构性变化→QLC NAND中期供给风险大幅降低。Mouser U.2库存昨日4台恢复(打破33天枯竭)但今日数据模糊→供给改善但未确认。E1.L 4台Day 16稳定。SS$31,500 In Stock。五渠道替代覆盖健康。MLC停产(8天)仍产生QLC需求溢出但强度弱于'双重收缩'场景。建议分批采购：对MLC溢出敏感的大容量位优先执行,其余分散到未来2-4周。321层QLC H2 2026出货→远期供给改善预期。"
    }
  },
  "gaps": [
    {
      "category": "DDR5-6400",
      "spec": "16GB",
      "reasonCode": "no_public_sample",
      "note": "企业级16GB RDIMM极少公开零售。Day 58。"
    },
    {
      "category": "DDR5-5600",
      "spec": "16GB",
      "reasonCode": "no_public_sample",
      "note": "同上。Day 58。"
    },
    {
      "category": "DDR5-5600",
      "spec": "96GB",
      "reasonCode": "stale_repeated_sample",
      "note": "NEMIX $3,200单一零售源Day 58。HPE/Dell/OEM交叉参考存在但未形成独立公开价带。第三十三次请求创建tracking列。"
    },
    {
      "category": "PCIe4 QLC",
      "spec": "61.44TB U.2 (Mouser stock)",
      "reasonCode": "parser_gap",
      "note": "Mouser搜索摘要显示1-5台,昨日直页验证4台。搜索片段分歧无法确定精确库存,需下次执行时定向产品页验证。"
    },
    {
      "category": "PCIe5 TLC",
      "spec": "30.72TB (CDW-G/SHI #2)",
      "reasonCode": "parser_gap",
      "note": "CDW-G需独立会员登录验证。SHI #2 ($20,496) 库存状态未获独立确认。"
    }
  ],
  "escalatedRisks": [
    {
      "risk": "DDR5 spot $46.000十七连ATH·四天空窗压力积累",
      "status": "今晚~18:00 session检验$47",
      "categoriesAffected": ["All DDR5"],
      "confidence": "high"
    },
    {
      "risk": "MLC NAND停产仅剩8天",
      "status": "最终六月发货·Line 12→HBM4 DRAM转换",
      "categoriesAffected": ["All SSD"],
      "confidence": "high"
    },
    {
      "risk": "WF6危机已解除(6/19)",
      "status": "停产暂停·地缘风险存续·韩供应商涨价待确认",
      "categoriesAffected": ["All SSD","All NAND"],
      "confidence": "high"
    },
    {
      "risk": "Newegg 9550 Pro OOS Day 15",
      "status": "两周+一天·第三工作周·结构性不可逆",
      "categoriesAffected": ["PCIe5 TLC"],
      "confidence": "high"
    },
    {
      "risk": "Micron 6/24财报·2天后",
      "status": "共识$34.52B/$19.72EPS·sell-the-news风险247WallSt预警",
      "categoriesAffected": ["All"],
      "confidence": "high"
    },
    {
      "risk": "Samsung PM1763 PCIe Gen6已推出",
      "status": "对PCIe5 TLC中期技术迭代压力·28,400MB/s vs PM1743~14,000MB/s",
      "categoriesAffected": ["PCIe5 TLC"],
      "confidence": "medium"
    }
  ]
}
